LICENSE
MANIFEST.in
README.md
setup.cfg
setup.py
opengraph/__init__.py
podiant_opengraph.egg-info/PKG-INFO
podiant_opengraph.egg-info/SOURCES.txt
podiant_opengraph.egg-info/dependency_links.txt
podiant_opengraph.egg-info/not-zip-safe
podiant_opengraph.egg-info/requires.txt
podiant_opengraph.egg-info/top_level.txt