Metadata-Version: 2.1
Name: podiant-opengraph
Version: 0.1.0
Summary: An Open Graph data parser
Home-page: https://git.steadman.io/podiant/opengraph
Author: Mark Steadman
Author-email: mark@podiant.co
License: MIT
Keywords: podiant-opengraph
Platform: UNKNOWN
Classifier: Development Status :: 3 - Alpha
Classifier: Intended Audience :: Developers
Classifier: License :: OSI Approved :: BSD License
Classifier: Natural Language :: English
Classifier: Programming Language :: Python :: 3
Classifier: Programming Language :: Python :: 3.4
Classifier: Programming Language :: Python :: 3.5
Classifier: Programming Language :: Python :: 3.6
